consumerism/__init__.py
consumerism/consumer.py
consumerism/dead_letter.py
consumerism/debug.py
consumerism/message.py
consumerism/persist.py
consumerism/processor.py
consumerism/resource.py
consumerism/resource_factory.py
consumerism/retry.py
consumerism/utils.py
consumerism-0.3.11.dist-info/DESCRIPTION.rst
consumerism-0.3.11.dist-info/METADATA
consumerism-0.3.11.dist-info/RECORD
consumerism-0.3.11.dist-info/WHEEL
consumerism-0.3.11.dist-info/metadata.json
consumerism-0.3.11.dist-info/top_level.txt
