Metadata-Version: 2.0
Name: consumerism
Version: 0.3.11
Summary: Expert360 Python SQS consumer library
Home-page: https://github.com/expert360/consumerism
Author: Expert360
Author-email: info@expert360.com
License: MIT
Keywords: boto sqs consumer
Platform: UNKNOWN
Classifier: Development Status :: 5 - Production/Stable
Classifier: Intended Audience :: Developers
Classifier: License :: OSI Approved :: MIT License
Classifier: Programming Language :: Python :: 2.7
Requires-Dist: boto (>=2.34.0)
